{
    "configurations": [
        {
            "name": "Linux",
            "includePath": [
                "${workspaceFolder}/**",
                "sdk/hollyhock2/sdk/include/**"
            ],
            "defines": [],
            "compilerPath": "/usr/bin/gcc",
            "cStandard": "c17",
            "cppStandard": "gnu++17",
            "intelliSenseMode": "linux-gcc-x64"
        },
        {
            "name": "sh4",
            "includePath": [
                "sdk/hollyhock2/sdk/include/**",
                "${workspaceFolder}/**"
            ],
            "defines": [],
            "compilerPath": "toolchain/sh4-tools/cross/bin/sh4-elf-gcc",
            "cStandard": "c17",
            "cppStandard": "gnu++17",
            "intelliSenseMode": "linux-gcc-x64"
        }
    ],
    "version": 4
}